setup.py
dsnd_distributions_SAS/Binomialdistribution.py
dsnd_distributions_SAS/Gaussiandistribution.py
dsnd_distributions_SAS/Generaldistribution.py
dsnd_distributions_SAS/__init__.py
dsnd_distributions_SAS.egg-info/PKG-INFO
dsnd_distributions_SAS.egg-info/SOURCES.txt
dsnd_distributions_SAS.egg-info/dependency_links.txt
dsnd_distributions_SAS.egg-info/not-zip-safe
dsnd_distributions_SAS.egg-info/top_level.txt