Metadata-Version: 1.0
Name: dsnd-distributions-SAS
Version: 0.1
Summary: Gaussian and binomial distributions
Home-page: UNKNOWN
Author: Samara Sadeek
Author-email: UNKNOWN
License: UNKNOWN
Platform: UNKNOWN
